forgeo/__init__.py
forgeo/__version__.py
forgeo/utils.py
forgeo/core/__init__.py
forgeo/core/data.py
forgeo/core/erosion.py
forgeo/core/faultnetwork.py
forgeo/core/model.py
forgeo/core/unit.py
forgeo/io/__init__.py
forgeo/io/xml/__init__.py
forgeo/io/xml/__main__.py
forgeo/io/xml/base.py
forgeo/io/xml/builtins.py
forgeo/io/xml/custom.py
forgeo/io/xml/ellipsoid.py
forgeo/io/xml/erosion.py
forgeo/io/xml/faultitem.py
forgeo/io/xml/faultnetwork.py
forgeo/io/xml/interpolator.py
forgeo/io/xml/item.py
forgeo/io/xml/model.py
forgeo/io/xml/neighborhood.py
forgeo/io/xml/unit.py
forgeo/io/xml/utils.py
forgeo/io/xml/variogram.py
forgeo-0.6.1.post1.dist-info/licenses/LICENSE
forgeo-0.6.1.post1.dist-info/METADATA
forgeo-0.6.1.post1.dist-info/WHEEL
forgeo-0.6.1.post1.dist-info/top_level.txt
forgeo-0.6.1.post1.dist-info/RECORD
