Metadata-Version: 2.4
Name: forgeo
Version: 0.6.1.post1
Summary: BRGM geological modelling framework
Author-email: BRGM <forgeo@brgm.fr>
Maintainer: Leana QUIMERCH, Nicolas CLAUSOLLES, Simon LOPEZ, Thomas JANVIER
License-Expression: AGPL-3.0-or-later
Project-URL: homepage, https://brgm.gitlab.io/geomodelling/forgeo/
Project-URL: repository, https://gitlab.com/brgm/geomodelling/forgeo-core
Requires-Python: >=3.3
License-File: LICENSE
Requires-Dist: attrs
Provides-Extra: test
Requires-Dist: pytest; extra == "test"
Requires-Dist: matplotlib; extra == "test"
Requires-Dist: vtkwriters; extra == "test"
Dynamic: license-file
